{"title":"Testat_1","markdown":{"yaml":{"title":"Testat_1"},"headingText":"Testat 1 - Aufgabenstellung","containsRefs":false,"markdown":"\n\n## Lagerkraft- und Schnittgrössen\n\nGegeben ist das statische System in @fig-system. Die Einwirkungen sind auf charakteristischem Niveau [^1]. \n\n[^1]: Charakteristisch bedeutet frei von Sicherheitsbeiwerten. Für diese Testatübung ist dies nicht relevant. \n\n![Ein einfacher Balken mit Streckenlast und Punktlasten](../images/Testat_01_HS23.svg){#fig-system}\n\nGesucht:\n\n- Zeichnen Sie ein Schnittkörperdiagramm des gesamten statischen Systems (SKD) und bestimmen Sie die Lagerkraftgrössen in $A$ und $B$.\n- Kontrollieren Sie Ihre Berechnung der Lagerkraftgrössen.\n- Bestimmen Sie die Schnittgrössen Normalkraft $N_x$, Querkraft $V_z$ und Biegemoment $M_y$ an der Stelle $x=4$ m. \n\n{{< pagebreak >}}\n\n# Testat 1 - Musterlösung\n\n## Schnittkörperdiagramm\n\nDas Schnittkörperdiagramm für das gesamte System ist in @fig-skd gezeigt. Es sind lediglich die Auflagersymbole durch entsprechende Reaktionskräfte zu ersetzen. Die Richtung der Vektoren (Kräfte) sind frei wählbar, sind jedoch mit entsprechenden Vorzeichen gemäss des unterlegenen Koordinatensystems (sowie des Drehsinns) in die Gleichgewichtsberechnungen einzusetzen.\n\n\n![Schnittkörperdiagramm des einfachen Balkens](../images/Testat_01_HS23_SKD.svg){#fig-skd}\n\n\n\n\n## Auflagerkräfte\n\nZuerst wird $B_z$ ermittelt, dies kann durch Gleichgewicht der Momente um Punkt $A$ geschehen.\n\n$$\n\\sum_A^\\curvearrowleft M_y = 0\n$${#eq-ggw_M_A}\n\nAnhand des Momentengleichgewichts um Punkt $B$ kann $A_z$ ermittelt werden.\n$$\n\\sum_B^\\curvearrowleft M_y = 0\n$${#eq-ggw_M_B}\n\nDie horizontale Auflagerreaktion $A_x$ kann durch Gleichgewicht der horizontalen Kräfte ermittelt werden:\n\n$$\n\\sum^\\rightarrow F_x = 0\n$${#eq-sum_fx}\n\n## Kontrolle der Lagerkraftgrössen\n\nDa beide Auflagerkräfte in $z$-Richtung mittels eines Momentengleichgewichts bestimmt worden sind, bleibt die Summe aller Kräfte in $z$-Richtung zur Kontrolle der Grössen.\n\n$$\n\\sum^\\uparrow F_z = 0\n$${#eq-ggw_fz}\n\nEs zeigt sich, dass die Gleichgewichtsbedingung auch in $z$-Richtung eingehalten ist.\n\n## Schnittkräfte \n\nDie Schnittkräfte lassen sich anhand eines SKDs bestimmen. Dabei ist das System an der gewünschten Stelle zu schneiden. Am Schnittufer sind die Schnittkräfte einzuführen. Dabei ist die Vorzeichenkonvention zu beachten, welche sich anhand des Schnittufers (positv / negativ) unterscheidet. Die Wahl des Schnittufers ist nicht relevant, da sich die Schnittkräfte an diesem Punkt im Gleichgewicht befinden, sind die Resultate identisch. \n\n![Schnittkörperdiagramm an der Stelle $x=4$m mit positivem Schnittufer](../images/Testat_01_HS23_SKD_1.svg){#fig-skd_4_pos}\n\n\n![Schnittkörperdiagramm an der Stelle $x=4$m mit negativem Schnittufer](../images/Testat_01_HS23_SKD_2.svg){#fig-skd_4_neg}\n\nDie @fig-skd_4_pos und @fig-skd_4_neg zeigen ein negatives und positives Schnittufer für die gleiche Stelle im System.\nZur Ermittlung der Schnittkräfte gilt es nun die Gleichgewichtsbedingungen anzuwenden.\n\nFür das System in @fig-skd_4_pos.\n\n$$\n\\sum_{x=4m}^\\uparrow F_z = 0\n$${#eq-ggw_fz2}\n\nZur Bestimmung der Normalkraft:\n\n$$\n\\sum_{x=4m}^\\rightarrow F_x = 0\n$${#eq-sum_fx2}\n\nLetztlich zur Bestimmung des Biegemoments:\n\n$$\n\\sum_{x=4m}^\\curvearrowleft M_y = 0\n$${#eq-ggw_M_B_4m}\n","srcMarkdownNoYaml":"\n\n# Testat 1 - Aufgabenstellung\n## Lagerkraft- und Schnittgrössen\n\nGegeben ist das statische System in @fig-system. Die Einwirkungen sind auf charakteristischem Niveau [^1]. \n\n[^1]: Charakteristisch bedeutet frei von Sicherheitsbeiwerten. Für diese Testatübung ist dies nicht relevant. \n\n![Ein einfacher Balken mit Streckenlast und Punktlasten](../images/Testat_01_HS23.svg){#fig-system}\n\nGesucht:\n\n- Zeichnen Sie ein Schnittkörperdiagramm des gesamten statischen Systems (SKD) und bestimmen Sie die Lagerkraftgrössen in $A$ und $B$.\n- Kontrollieren Sie Ihre Berechnung der Lagerkraftgrössen.\n- Bestimmen Sie die Schnittgrössen Normalkraft $N_x$, Querkraft $V_z$ und Biegemoment $M_y$ an der Stelle $x=4$ m. \n\n{{< pagebreak >}}\n\n# Testat 1 - Musterlösung\n\n## Schnittkörperdiagramm\n\nDas Schnittkörperdiagramm für das gesamte System ist in @fig-skd gezeigt. Es sind lediglich die Auflagersymbole durch entsprechende Reaktionskräfte zu ersetzen. Die Richtung der Vektoren (Kräfte) sind frei wählbar, sind jedoch mit entsprechenden Vorzeichen gemäss des unterlegenen Koordinatensystems (sowie des Drehsinns) in die Gleichgewichtsberechnungen einzusetzen.\n\n\n![Schnittkörperdiagramm des einfachen Balkens](../images/Testat_01_HS23_SKD.svg){#fig-skd}\n\n\n\n\n## Auflagerkräfte\n\nZuerst wird $B_z$ ermittelt, dies kann durch Gleichgewicht der Momente um Punkt $A$ geschehen.\n\n$$\n\\sum_A^\\curvearrowleft M_y = 0\n$${#eq-ggw_M_A}\n\nAnhand des Momentengleichgewichts um Punkt $B$ kann $A_z$ ermittelt werden.\n$$\n\\sum_B^\\curvearrowleft M_y = 0\n$${#eq-ggw_M_B}\n\nDie horizontale Auflagerreaktion $A_x$ kann durch Gleichgewicht der horizontalen Kräfte ermittelt werden:\n\n$$\n\\sum^\\rightarrow F_x = 0\n$${#eq-sum_fx}\n\n## Kontrolle der Lagerkraftgrössen\n\nDa beide Auflagerkräfte in $z$-Richtung mittels eines Momentengleichgewichts bestimmt worden sind, bleibt die Summe aller Kräfte in $z$-Richtung zur Kontrolle der Grössen.\n\n$$\n\\sum^\\uparrow F_z = 0\n$${#eq-ggw_fz}\n\nEs zeigt sich, dass die Gleichgewichtsbedingung auch in $z$-Richtung eingehalten ist.\n\n## Schnittkräfte \n\nDie Schnittkräfte lassen sich anhand eines SKDs bestimmen. Dabei ist das System an der gewünschten Stelle zu schneiden. Am Schnittufer sind die Schnittkräfte einzuführen. Dabei ist die Vorzeichenkonvention zu beachten, welche sich anhand des Schnittufers (positv / negativ) unterscheidet. Die Wahl des Schnittufers ist nicht relevant, da sich die Schnittkräfte an diesem Punkt im Gleichgewicht befinden, sind die Resultate identisch. \n\n![Schnittkörperdiagramm an der Stelle $x=4$m mit positivem Schnittufer](../images/Testat_01_HS23_SKD_1.svg){#fig-skd_4_pos}\n\n\n![Schnittkörperdiagramm an der Stelle $x=4$m mit negativem Schnittufer](../images/Testat_01_HS23_SKD_2.svg){#fig-skd_4_neg}\n\nDie @fig-skd_4_pos und @fig-skd_4_neg zeigen ein negatives und positives Schnittufer für die gleiche Stelle im System.\nZur Ermittlung der Schnittkräfte gilt es nun die Gleichgewichtsbedingungen anzuwenden.\n\nFür das System in @fig-skd_4_pos.\n\n$$\n\\sum_{x=4m}^\\uparrow F_z = 0\n$${#eq-ggw_fz2}\n\nZur Bestimmung der Normalkraft:\n\n$$\n\\sum_{x=4m}^\\rightarrow F_x = 0\n$${#eq-sum_fx2}\n\nLetztlich zur Bestimmung des Biegemoments:\n\n$$\n\\sum_{x=4m}^\\curvearrowleft M_y = 0\n$${#eq-ggw_M_B_4m}\n"},"formats":{"pdf":{"identifier":{"display-name":"PDF","target-format":"pdf","base-format":"pdf"},"execute":{"fig-width":5.5,"fig-height":3.5,"fig-format":"svg","fig-dpi":300,"df-print":"default","error":false,"eval":true,"cache":null,"freeze":false,"echo":false,"output":true,"warning":false,"include":true,"keep-md":false,"keep-ipynb":false,"ipynb":null,"enabled":false,"daemon":null,"daemon-restart":false,"debug":false,"ipynb-filters":[],"engine":"jupyter"},"render":{"keep-tex":false,"keep-source":false,"keep-hidden":false,"prefer-html":false,"output-divs":true,"output-ext":"pdf","fig-align":"default","fig-pos":"H","fig-env":null,"code-fold":"none","code-overflow":"scroll","code-link":false,"code-line-numbers":false,"code-tools":false,"tbl-colwidths":[50,50],"merge-includes":true,"inline-includes":false,"preserve-yaml":false,"latex-auto-mk":true,"latex-auto-install":true,"latex-clean":true,"latex-max-runs":10,"latex-makeindex":"makeindex","latex-makeindex-opts":[],"latex-tlmgr-opts":[],"latex-input-paths":[],"latex-output-dir":null,"link-external-icon":false,"link-external-newwindow":false,"self-contained-math":false,"format-resources":[]},"pandoc":{"pdf-engine":"xelatex","standalone":true,"variables":{"graphics":true,"tables":true},"default-image-extension":"pdf","to":"pdf","include-in-header":["../src/utils/hslu_style.sty"],"toc-depth":3,"output-file":"BSI_HS23_Testat_01.pdf"},"language":{"toc-title-document":"Inhaltsverzeichnis","toc-title-website":"Auf dieser Seite","related-formats-title":"Andere Formate","related-notebooks-title":"Notebooks","source-notebooks-prefix":"Quelle","section-title-abstract":"Zusammenfassung","section-title-appendices":"Anhang","section-title-footnotes":"Fußnoten","section-title-references":"Literatur","section-title-reuse":"Wiederverwendung","section-title-copyright":"Urheberrechte","section-title-citation":"Zitat","appendix-attribution-cite-as":"Bitte zitieren Sie diese Arbeit als:","appendix-attribution-bibtex":"Mit BibTeX zitieren:","title-block-author-single":"Autor:in","title-block-author-plural":"Autor:innen","title-block-affiliation-single":"Zugehörigkeit","title-block-affiliation-plural":"Zugehörigkeiten","title-block-published":"Veröffentlichungsdatum","title-block-modified":"Geändert","callout-tip-title":"Tipp","callout-note-title":"Hinweis","callout-warning-title":"Warnung","callout-important-title":"Wichtig","callout-caution-title":"Vorsicht","code-summary":"Code","code-tools-menu-caption":"Code","code-tools-show-all-code":"Gesamten Code zeigen","code-tools-hide-all-code":"Gesamten Code verbergen","code-tools-view-source":"Quellcode anzeigen","code-tools-source-code":"Quellcode","code-line":"Zeile","code-lines":"Zeilen","copy-button-tooltip":"In die Zwischenablage kopieren","copy-button-tooltip-success":"Kopiert","repo-action-links-edit":"Seite editieren","repo-action-links-source":"Quellcode anzeigen","repo-action-links-issue":"Problem melden","back-to-top":"Zurück nach oben","search-no-results-text":"Keine Treffer","search-matching-documents-text":"Treffer","search-copy-link-title":"Link in die Suche kopieren","search-hide-matches-text":"Zusätzliche Treffer verbergen","search-more-match-text":"weitere Treffer in diesem Dokument","search-more-matches-text":"weitere Treffer in diesem Dokument","search-clear-button-title":"Zurücksetzen","search-detached-cancel-button-title":"Abbrechen","search-submit-button-title":"Abschicken","search-label":"Suchen","toggle-section":"Abschnitt umschalten","toggle-sidebar":"Seitenleiste umschalten","toggle-dark-mode":"Dunkelmodus umschalten","toggle-reader-mode":"Lesemodus umschalten","toggle-navigation":"Navigation umschalten","crossref-fig-title":"Abbildung","crossref-tbl-title":"Tabelle","crossref-lst-title":"Listing","crossref-thm-title":"Theorem","crossref-lem-title":"Lemma","crossref-cor-title":"Korollar","crossref-prp-title":"Aussage","crossref-cnj-title":"Annahme","crossref-def-title":"Definition","crossref-exm-title":"Beispiel","crossref-exr-title":"Übungsaufgabe","crossref-ch-prefix":"Kapitel","crossref-apx-prefix":"Anhang","crossref-sec-prefix":"Kapitel","crossref-eq-prefix":"Gleichung","crossref-lof-title":"Abbildungsverzeichnis","crossref-lot-title":"Tabellenverzeichnis","crossref-lol-title":"Listingverzeichnis","environment-proof-title":"Beweis","environment-remark-title":"Anmerkung","environment-solution-title":"Lösung","listing-page-order-by":"Sortieren nach","listing-page-order-by-default":"Voreinstellung","listing-page-order-by-date-asc":"Datum (aufsteigend)","listing-page-order-by-date-desc":"Neueste","listing-page-order-by-number-desc":"Absteigend","listing-page-order-by-number-asc":"Aufsteigend","listing-page-field-date":"Datum","listing-page-field-title":"Titel","listing-page-field-description":"Beschreibung","listing-page-field-author":"Autor:in","listing-page-field-filename":"Dateiname","listing-page-field-filemodified":"Geändert","listing-page-field-subtitle":"Untertitel","listing-page-field-readingtime":"Lesezeit","listing-page-field-categories":"Kategorien","listing-page-minutes-compact":"{0} min","listing-page-category-all":"alle","listing-page-no-matches":"Keine Treffer"},"metadata":{"block-headings":true,"bibliography":["../literatur/literatur.bib"],"documentclass":"scrartcl","lang":"de","csl":"diabetologia.csl","link-citations":true,"mainfont":"Palatino Linotype","fontsize":"12pt","classoption":"egregdoesnotlikesansseriftitles","title":"Testat_1"},"extensions":{"book":{"selfContainedOutput":true}}}},"projectFormats":["pdf"]}